flux_mcp/__init__.py
flux_mcp/registry.py
flux_mcp/version.py
flux_mcp/job/__init__.py
flux_mcp/job/core.py
flux_mcp/job/delegate.py
flux_mcp/logger/__init__.py
flux_mcp/logger/generate.py
flux_mcp/logger/logger.py
flux_mcp/sched/__init__.py
flux_mcp/sched/cancel.py
flux_mcp/sched/graph.py
flux_mcp/sched/info.py
flux_mcp/sched/initialize.py
flux_mcp/sched/match_allocate.py
flux_mcp/server/__init__.py
flux_mcp/server/__main__.py
flux_mcp/server/fastmcp/__main__.py
flux_mcp/server/fastmcp/app.py
flux_mcp/server/fastmcp/middleware/__init__.py
flux_mcp/server/fastmcp/middleware/token_auth.py
flux_mcp/transformer/__init__.py
flux_mcp/transformer/base.py
flux_mcp/transformer/common.py
flux_mcp/transformer/prompts.py
flux_mcp/transformer/registry.py
flux_mcp/transformer/tool.py
flux_mcp/transformer/cobalt/__init__.py
flux_mcp/transformer/cobalt/transform.py
flux_mcp/transformer/flux/__init__.py
flux_mcp/transformer/flux/transform.py
flux_mcp/transformer/kubernetes/__init__.py
flux_mcp/transformer/kubernetes/transform.py
flux_mcp/transformer/lsf/__init__.py
flux_mcp/transformer/lsf/transform.py
flux_mcp/transformer/moab/__init__.py
flux_mcp/transformer/moab/transform.py
flux_mcp/transformer/oar/__init__.py
flux_mcp/transformer/oar/transform.py
flux_mcp/transformer/pbs/__init__.py
flux_mcp/transformer/pbs/transform.py
flux_mcp/transformer/slurm/__init__.py
flux_mcp/transformer/slurm/transform.py
flux_mcp/utils/__init__.py
flux_mcp/utils/fileio.py
flux_mcp/utils/text.py
flux_mcp/utils/timer.py
flux_mcp/validate/__init__.py
flux_mcp/validate/prompts.py
flux_mcp/validate/tools.py
flux_mcp/validate/validate.py
flux_mcp-0.0.14.dist-info/LICENSE
flux_mcp-0.0.14.dist-info/METADATA
flux_mcp-0.0.14.dist-info/NOTICE
flux_mcp-0.0.14.dist-info/WHEEL
flux_mcp-0.0.14.dist-info/entry_points.txt
flux_mcp-0.0.14.dist-info/top_level.txt
flux_mcp-0.0.14.dist-info/RECORD
